rpc_component/__init__.py
rpc_component/cli.py
rpc_component/component.py
rpc_component/schemata.py
rpc_component-0.0.2.dist-info/LICENSE.txt
rpc_component-0.0.2.dist-info/METADATA
rpc_component-0.0.2.dist-info/WHEEL
rpc_component-0.0.2.dist-info/entry_points.txt
rpc_component-0.0.2.dist-info/top_level.txt
rpc_component-0.0.2.dist-info/RECORD
